sts_saml_driver.py
sts_saml_driver-1.0.3.dist-info/licenses/LICENSE
sts_saml_driver-1.0.3.dist-info/licenses/NOTICE
sts_saml_driver-1.0.3.dist-info/METADATA
sts_saml_driver-1.0.3.dist-info/WHEEL
sts_saml_driver-1.0.3.dist-info/entry_points.txt
sts_saml_driver-1.0.3.dist-info/top_level.txt
sts_saml_driver-1.0.3.dist-info/RECORD
