Metadata-Version: 2.4
Name: sts_saml_driver
Version: 1.0.3
Summary: A utility to capture SAML assertions and use them to get AWS credentials without browser emulation
Home-page: https://github.com/awslabs/StsSamlDriver
Author: Liam Wadman
Author-email: liwadman@amazon.com
Classifier: Programming Language :: Python :: 3
Classifier: License :: OSI Approved :: MIT License
Classifier: Operating System :: OS Independent
Requires-Python: >=3.10
License-File: LICENSE
License-File: NOTICE
Requires-Dist: requests
Requires-Dist: bottle
Requires-Dist: boto3
Requires-Dist: urllib3
Dynamic: author
Dynamic: author-email
Dynamic: classifier
Dynamic: home-page
Dynamic: license-file
Dynamic: requires-dist
Dynamic: requires-python
Dynamic: summary
